database_automation/__init__.py
database_automation/mongo_crud.py
database_mongodb-0.0.11.dist-info/METADATA
database_mongodb-0.0.11.dist-info/WHEEL
database_mongodb-0.0.11.dist-info/top_level.txt
database_mongodb-0.0.11.dist-info/RECORD
